tesselite/__init__.py
tesselite/config.py
tesselite/exceptions.py
tesselite/logger.py
tesselite/pubsub.py
tesselite/samples.py
tesselite/schemas.py
tesselite/tests/__init__.py
tesselite/tests/main.py
tesselite/tests/test_gcp.py
tesselite/tests/test_rabbitmq.py
tesselite/tests/test_redis.py
tesselite_pubsub-0.2.2.dist-info/LICENSE
tesselite_pubsub-0.2.2.dist-info/METADATA
tesselite_pubsub-0.2.2.dist-info/WHEEL
tesselite_pubsub-0.2.2.dist-info/entry_points.txt
tesselite_pubsub-0.2.2.dist-info/RECORD
