Metadata-Version: 2.3
Name: tesselite-pubsub
Version: 0.2.2
Summary: general sugarcoat for all pubsub flavors.
License: MIT
Author: Marcel Ndeffo
Author-email: marcel.nasser@live.fr
Requires-Python: >=3.9
Classifier: License :: OSI Approved :: MIT License
Classifier: Programming Language :: Python :: 3
Classifier: Programming Language :: Python :: 3.9
Classifier: Programming Language :: Python :: 3.10
Classifier: Programming Language :: Python :: 3.11
Classifier: Programming Language :: Python :: 3.12
Classifier: Programming Language :: Python :: 3.13
Requires-Dist: google-cloud-pubsub (>=2.26.1,<3.0.0)
Requires-Dist: pika (>=1.3.2,<2.0.0)
Requires-Dist: python-dotenv (>=1.0.1,<2.0.0)
Requires-Dist: redis (>=5.1.1,<6.0.0)
Requires-Dist: retry (>=0.9.2,<0.10.0)
